fusionauth_client-1.62.0-py3.12-nspkg.pth
fusionauth/fusionauth_client.py
fusionauth/rest_client.py
fusionauth_client-1.62.0.dist-info/licenses/LICENSE
fusionauth_client-1.62.0.dist-info/METADATA
fusionauth_client-1.62.0.dist-info/WHEEL
fusionauth_client-1.62.0.dist-info/namespace_packages.txt
fusionauth_client-1.62.0.dist-info/top_level.txt
fusionauth_client-1.62.0.dist-info/RECORD
