Metadata-Version: 2.4
Name: fusionauth-client
Version: 1.62.0
Summary: A client library for FusionAuth
Home-page: https://github.com/FusionAuth/fusionauth-python-client
Author: FusionAuth
Author-email: dev@fusionauth.io
Classifier: Programming Language :: Python :: 3
Classifier: License :: OSI Approved :: Apache Software License
Classifier: Operating System :: OS Independent
Classifier: Topic :: Software Development :: Libraries
License-File: LICENSE
Requires-Dist: deprecated
Requires-Dist: requests
Dynamic: author
Dynamic: author-email
Dynamic: classifier
Dynamic: description
Dynamic: description-content-type
Dynamic: home-page
Dynamic: license-file
Dynamic: requires-dist
Dynamic: summary
